dictdb.py
DictDB-0.0.0.dist-info/DESCRIPTION.rst
DictDB-0.0.0.dist-info/METADATA
DictDB-0.0.0.dist-info/pydist.json
DictDB-0.0.0.dist-info/RECORD
DictDB-0.0.0.dist-info/top_level.txt
DictDB-0.0.0.dist-info/WHEEL
