Metadata-Version: 2.0
Name: DictDB
Version: 0.0.0
Summary: A scheem free database by useing python dict
Home-page: https://github.com/toomore/dictDB
Author: Toomore Chiang
Author-email: toomore0929@gmail.com
License: MIT
Keywords: dict schema-free database
Platform: UNKNOWN
Classifier: Development Status :: 2 - Pre-Alpha
Classifier: Environment :: Console
Classifier: Intended Audience :: End Users/Desktop
Classifier: Intended Audience :: Developers
Classifier: License :: OSI Approved :: MIT License
Classifier: Natural Language :: Chinese (Traditional)
Classifier: Programming Language :: Python
Classifier: Programming Language :: Python :: 2.7
Classifier: Topic :: Database :: Front-Ends
Requires-Dist: ujson
